pyPandey/__init__.py
pyPandey/__main__.py
pyPandey/configs.py
pyPandey/exceptions.py
pyPandey/loader.py
pyPandey/version.py
pyPandey/_misc/__init__.py
pyPandey/_misc/_assistant.py
pyPandey/_misc/_decorators.py
pyPandey/_misc/_supporter.py
pyPandey/_misc/_wrappers.py
pyPandey/dB/__init__.py
pyPandey/dB/_core.py
pyPandey/dB/afk_db.py
pyPandey/dB/antiflood_db.py
pyPandey/dB/asst_fns.py
pyPandey/dB/asstcmd_db.py
pyPandey/dB/autoban_db.py
pyPandey/dB/blacklist_chat_db.py
pyPandey/dB/blacklist_db.py
pyPandey/dB/botchat_db.py
pyPandey/dB/broadcast_db.py
pyPandey/dB/ch_db.py
pyPandey/dB/dnd_db.py
pyPandey/dB/echo_db.py
pyPandey/dB/filestore_db.py
pyPandey/dB/filter_db.py
pyPandey/dB/forcesub_db.py
pyPandey/dB/gban_mute_db.py
pyPandey/dB/gcast_blacklist_db.py
pyPandey/dB/greetings_db.py
pyPandey/dB/logusers_db.py
pyPandey/dB/mute_db.py
pyPandey/dB/night_db.py
pyPandey/dB/notes_db.py
pyPandey/dB/nsfw_db.py
pyPandey/dB/pmpermit_db.py
pyPandey/dB/snips_db.py
pyPandey/dB/vc_sudos.py
pyPandey/dB/warn_db.py
pyPandey/functions/FastTelethon.py
pyPandey/functions/__init__.py
pyPandey/functions/admins.py
pyPandey/functions/executor.py
pyPandey/functions/gDrive.py
pyPandey/functions/google_image.py
pyPandey/functions/helper.py
pyPandey/functions/info.py
pyPandey/functions/misc.py
pyPandey/functions/tools.py
pyPandey/functions/ytdl.py
pyPandey/startup/BaseClient.py
pyPandey/startup/__init__.py
pyPandey/startup/_database.py
pyPandey/startup/_extra.py
pyPandey/startup/connections.py
pyPandey/startup/funcs.py
pyPandey/startup/loader.py
pyPandey/startup/utils.py
pyPandey-2024.11.12.dist-info/LICENSE
pyPandey-2024.11.12.dist-info/METADATA
pyPandey-2024.11.12.dist-info/WHEEL
pyPandey-2024.11.12.dist-info/top_level.txt
pyPandey-2024.11.12.dist-info/RECORD
