Metadata-Version: 2.1
Name: pyPandey
Version: 2024.11.12
Summary: A Secure and Powerful Python-Telethon Based Library For Pragyan Userbot.
Home-page: https://github.com/TeamPandey/pyPandey
Author: TeamPandey
Author-email: pragyanspandey@gmail.com
License: GNU AFFERO GENERAL PUBLIC LICENSE (v3)
Project-URL: Bug Tracker, https://github.com/TeamPandey/pyPandey/issues
Project-URL: Documentation, https://pragyan.tech
Project-URL: Source Code, https://github.com/TeamPandey/pyPandey
Classifier: Programming Language :: Python :: 3
Classifier: Programming Language :: Python :: 3.8
Classifier: Programming Language :: Python :: 3.9
Classifier: Programming Language :: Python :: 3.10
Classifier: License :: OSI Approved :: GNU General Public License v3 (GPLv3)
Classifier: Operating System :: OS Independent
Requires-Python: >3.7, <3.11
License-File: LICENSE
Requires-Dist: redis
Requires-Dist: hiredis
Requires-Dist: python-decouple
Requires-Dist: python-dotenv
